{
    "homepage": "https://multimc.org/",
    "version": "0.6.6",
	"url": "https://github.com/MultiMC/MultiMC5/releases/download/0.6.6/mmc-stable-win32.zip",
	"hash": "af52ac2577693a1b4e20293e0b5a3a8062fc5afac839b27cbad0356b85918f2b",
	"extract_dir": "MultiMC",
    "shortcuts": [
        [
            "MultiMC.exe",
            "MultiMC"
        ]
    ],
    "checkver": {
		"url": "https://github.com/MultiMC/MultiMC5/releases",
		"re": "<a href=\"/MultiMC/MultiMC5/releases/tag/([\\d.]+)\">"
	},
	"persist": [
		"accounts.json",
		"multimc.cfg",
		"instances",
		"accounts",
		"assets",
		"cache",
		"icons",
		"libraries",
		"meta",
		"themes"
	],
	"pre_install": "Add-Content \"$dir\\accounts.json\" $null; Add-Content \"$dir\\multimc.cfg\" $null",
	"notes": "Do not use the built-in updater to update MultiMC."
}
